aiotradier/__init__.py
aiotradier/common.py
aiotradier/const.py
aiotradier/exceptions.py
aiotradier/tradier_rest.py
aiotradier-0.0.9.dist-info/LICENSE
aiotradier-0.0.9.dist-info/METADATA
aiotradier-0.0.9.dist-info/WHEEL
aiotradier-0.0.9.dist-info/top_level.txt
aiotradier-0.0.9.dist-info/RECORD
